gilgalad/__init__.py
gilgalad/graph.py
gilgalad/layers.py
gilgalad/models.py
gilgalad/opt.py
gilgalad/plotting.py
gilgalad/utils.py
Gil_Galad-0.1.dist-info/LICENSE
Gil_Galad-0.1.dist-info/METADATA
Gil_Galad-0.1.dist-info/WHEEL
Gil_Galad-0.1.dist-info/top_level.txt
Gil_Galad-0.1.dist-info/RECORD
