Metadata-Version: 2.1
Name: Gil-Galad
Version: 0.1
Summary: A deep learning project template for TensorFlow
Home-page: https://github.com/davidreiman/Gil-Galad
Author: David Reiman
Author-email: dreiman@ucsc.edu
Maintainer: David Reiman
Maintainer-email: dreiman@ucsc.edu
License: GPLv3
Keywords: deep-learning tensorflow machine-learning
Platform: UNKNOWN
Classifier: Development Status :: 3 - Alpha
Classifier: Programming Language :: Python :: 3
Classifier: License :: OSI Approved :: GNU General Public License v3 (GPLv3)
Requires-Dist: tensorflow (>=1.7.0)
Requires-Dist: numpy (>=1.13.3)
Requires-Dist: parameter-sherpa
Requires-Dist: tqdm
Requires-Dist: progress
